<?xml version="1.0" encoding="utf-8"?>
<report report="任务2022-11-16T14-28-28-548526报告">
	<summary>
		<taskname>2022-11-16T14-28-28-548526</taskname>
		<creat_time>2022-11-16T14-28-28-548526</creat_time>
		<protocol>DongJian_TCP</protocol>
		<host_ip>172.16.145.25</host_ip>
		<port>0</port>
		<fuzzing_param></fuzzing_param>
	</summary>
	<task_info>
		<total_cases>N/A</total_cases>
		<tested_cases>263</tested_cases>
		<start_time>2022-11-16T14-28-28-548526</start_time>
		<end_time>2022-11-16T14-29-00-407316</end_time>
		<time_consuming>31秒</time_consuming>
		<task_status>finished</task_status>
	</task_info>
	<crash>
		<crash_node></crash_node>
	</crash>
</report>
